simplelayout/__init__.py
simplelayout/__main__.py
simplelayout/cli/__init__.py
simplelayout/cli/cli_generate.py
simplelayout/generator/__init__.py
simplelayout/generator/core.py
simplelayout/generator/utils.py
simplelayout_baokairui-1.1.0.dist-info/METADATA
simplelayout_baokairui-1.1.0.dist-info/WHEEL
simplelayout_baokairui-1.1.0.dist-info/entry_points.txt
simplelayout_baokairui-1.1.0.dist-info/top_level.txt
simplelayout_baokairui-1.1.0.dist-info/RECORD
